{
    "schedule": [
     {
        "id": 1,
        "date": "27/02/2024",
        "team1": "B-tech CS 2nd Year",
        "team2": "B-tech CE 2nd Year",
        "timing": "5:00PM - 7:30PM"
      },
     {
        "id": 2,
        "date": "27/02/2024",
        "team1": "MBA-tech CE 1st Year",
        "team2": " B-tech CS 3rd Year",
        "timing": "5:00PM - 7:30PM"
      },
      {
        "id": 3,
        "date": "22/02/2024",
        "team1": "B-tech CE 1st Year",
        "team2": "B-tech AIML 3rd year",
        "timing": "5:00PM - 7:30PM"
      }
      
    ],
    
    
  }
